[
  {
    "post_id": 6815289697549,
    "expected_comment_count": 3,
    "actual_comment_count": 3,
    "status": "ok",
    "comments": [
      {
        "id": 7627826211597,
        "body": "<p>There is several Redstone machines that make good use of them not breaking apart, but I would like to see an option that you can place in crafting 2X2 or 3X3 and break them apart</p>",
        "author_id": 398702531551,
        "vote_sum": 3,
        "vote_count": 3,
        "official": false,
        "html_url": "https://feedback.minecraft.net/hc/en-us/community/posts/6815289697549-Remove-Chest-from-Minecart-Chest/comments/7627826211597",
        "created_at": "2022-07-12T18:08:07Z",
        "updated_at": "2022-08-26T23:21:59Z",
        "url": "https://minecraftfeedback.zendesk.com/api/v2/help_center/community/posts/6815289697549/comments/7627826211597.json",
        "post_id": 6815289697549,
        "non_author_editor_id": null,
        "non_author_updated_at": null
      },
      {
        "id": 8362671171469,
        "body": "<p>I suggest that the Minecart with Block items be given the same property as the Bucket of Fluid items.</p>\n<p><br>So that, you may take the Block out of a Minecart with Block via crafting result,</p>\n<p>and the Minecart is returned to you empty just like how a Bucket is when used as an ingredient.</p>",
        "author_id": 423868859071,
        "vote_sum": 6,
        "vote_count": 6,
        "official": false,
        "html_url": "https://feedback.minecraft.net/hc/en-us/community/posts/6815289697549-Remove-Chest-from-Minecart-Chest/comments/8362671171469",
        "created_at": "2022-08-12T00:41:08Z",
        "updated_at": "2023-07-27T02:58:07Z",
        "url": "https://minecraftfeedback.zendesk.com/api/v2/help_center/community/posts/6815289697549/comments/8362671171469.json",
        "post_id": 6815289697549,
        "non_author_editor_id": null,
        "non_author_updated_at": null
      },
      {
        "id": 37032717537805,
        "body": "<p>The change to stop minecarts from dropping chests and hoppers seems a bit ironic now that the Crafter exists. It seems like originally we asked for \"Minecart with X\" to stop breaking into component parts because re-crafting them was a pain.<br><br>Now we have the opposite problem where it would be easy to re-craft them but we have no way to break them apart.</p>",
        "author_id": 401463233571,
        "vote_sum": 1,
        "vote_count": 1,
        "official": false,
        "html_url": "https://feedback.minecraft.net/hc/en-us/community/posts/6815289697549-Remove-Chest-from-Minecart-Chest/comments/37032717537805",
        "created_at": "2025-05-30T19:25:20Z",
        "updated_at": "2025-05-30T19:49:19Z",
        "url": "https://minecraftfeedback.zendesk.com/api/v2/help_center/community/posts/6815289697549/comments/37032717537805.json",
        "post_id": 6815289697549,
        "non_author_editor_id": null,
        "non_author_updated_at": null
      }
    ]
  },
  {
    "post_id": 4423535564429,
    "expected_comment_count": 5,
    "actual_comment_count": 5,
    "status": "ok",
    "comments": [
      {
        "id": 4423870123021,
        "body": "<p>just get a trident with loyalty dude</p>",
        "author_id": 423559997732,
        "vote_sum": 3,
        "vote_count": 3,
        "official": false,
        "html_url": "https://feedback.minecraft.net/hc/en-us/community/posts/4423535564429-Boomerang/comments/4423870123021",
        "created_at": "2022-02-02T07:15:50Z",
        "updated_at": "2022-12-14T23:16:57Z",
        "url": "https://minecraftfeedback.zendesk.com/api/v2/help_center/community/posts/4423535564429/comments/4423870123021.json",
        "post_id": 4423535564429,
        "non_author_editor_id": null,
        "non_author_updated_at": null
      },
      {
        "id": 4423884516237,
        "body": "<p>well if this was added it should have it so that sometimes it hits you.</p>\n<p>or misses you and lands somewhere else</p>",
        "author_id": 1901215708607,
        "vote_sum": 1,
        "vote_count": 1,
        "official": false,
        "html_url": "https://feedback.minecraft.net/hc/en-us/community/posts/4423535564429-Boomerang/comments/4423884516237",
        "created_at": "2022-02-02T07:41:04Z",
        "updated_at": "2022-02-07T18:41:35Z",
        "url": "https://minecraftfeedback.zendesk.com/api/v2/help_center/community/posts/4423535564429/comments/4423884516237.json",
        "post_id": 4423535564429,
        "non_author_editor_id": null,
        "non_author_updated_at": null
      },
      {
        "id": 4423872148877,
        "body": "<p>It might be in the savannah update in the future.</p>",
        "author_id": 1905008397287,
        "vote_sum": 1,
        "vote_count": 1,
        "official": false,
        "html_url": "https://feedback.minecraft.net/hc/en-us/community/posts/4423535564429-Boomerang/comments/4423872148877",
        "created_at": "2022-02-02T10:12:26Z",
        "updated_at": "2022-02-02T20:12:17Z",
        "url": "https://minecraftfeedback.zendesk.com/api/v2/help_center/community/posts/4423535564429/comments/4423872148877.json",
        "post_id": 4423535564429,
        "non_author_editor_id": null,
        "non_author_updated_at": null
      },
      {
        "id": 4424456443021,
        "body": "<p>The ability to hit a mob twice with one throw if you throw it right could be nice, I enjoy using boomerangs in games.</p>\n<p>It also could have the niche of being the weakest projectile weapon on each individual hit, but much easier to obtain than a trident, and not requiring separate ammo like a bow/crossbow. A skilled player could still craft several boomerangs and deftly alternate between using them to make up for the lack of power.</p>",
        "author_id": 409781224831,
        "vote_sum": 0,
        "vote_count": 0,
        "official": false,
        "html_url": "https://feedback.minecraft.net/hc/en-us/community/posts/4423535564429-Boomerang/comments/4424456443021",
        "created_at": "2022-02-06T22:39:32Z",
        "updated_at": "2022-02-09T21:48:30Z",
        "url": "https://minecraftfeedback.zendesk.com/api/v2/help_center/community/posts/4423535564429/comments/4424456443021.json",
        "post_id": 4423535564429,
        "non_author_editor_id": null,
        "non_author_updated_at": null
      },
      {
        "id": 4424566209549,
        "body": "<p>The Boomerang should be able to be thrown to get dropped loot or other items including xp and bring all of it back to you.&nbsp; Throwing the boomerang should take durability points when it connects with an object or player.&nbsp; Boomerangs can be enchanted similarly to a sword, especially with knockback, mending, and unbreaking.&nbsp;&nbsp;</p>",
        "author_id": 395370003811,
        "vote_sum": 0,
        "vote_count": 0,
        "official": false,
        "html_url": "https://feedback.minecraft.net/hc/en-us/community/posts/4423535564429-Boomerang/comments/4424566209549",
        "created_at": "2022-02-07T20:10:44Z",
        "updated_at": "2022-02-07T20:10:44Z",
        "url": "https://minecraftfeedback.zendesk.com/api/v2/help_center/community/posts/4423535564429/comments/4424566209549.json",
        "post_id": 4423535564429,
        "non_author_editor_id": null,
        "non_author_updated_at": null
      }
    ]
  },
  {
    "post_id": 4419696391053,
    "expected_comment_count": 4,
    "actual_comment_count": 4,
    "status": "ok",
    "comments": [
      {
        "id": 4419737123341,
        "body": "<p>the log should be dark gray<br>and the tree that gives more shadow <br>and it gives you more shoots</p>\n<p>it grows better in the lakes or swamps</p>\n<p>&nbsp;</p>",
        "author_id": 423195033631,
        "vote_sum": 4,
        "vote_count": 4,
        "official": false,
        "html_url": "https://feedback.minecraft.net/hc/en-us/community/posts/4419696391053-Weeping-willow-trees-with-white-wood/comments/4419737123341",
        "created_at": "2022-01-09T20:15:29Z",
        "updated_at": "2022-01-12T08:14:29Z",
        "url": "https://minecraftfeedback.zendesk.com/api/v2/help_center/community/posts/4419696391053/comments/4419737123341.json",
        "post_id": 4419696391053,
        "non_author_editor_id": null,
        "non_author_updated_at": null
      },
      {
        "id": 4420280832525,
        "body": "<p>Either dark gray or white would be cool, although I think birch is already white enough for me, so my vote is for dark gray. It would go great with modern builds. Maybe the tree could be unique in that it only generates naturally up to a certain distance from water.</p>\n<p>Other idea: mangrove trees that&nbsp;<em>only&nbsp;</em>grow in water. And/or maybe one of the two trees could be the first tree to self-propagate, meaning it could occasionally generate shoots (i.e. saplings) occasionally, which could grow into new trees. If it was mangroves this phenomenon could be limited by water depth.</p>\n<p>I think a self-propagating tree could be really cool because it would add an aspect of trees growing after world generation, and players having to \"weed out\" a species of tree (but it wouldn't get too out of control because it would be limited by either distance from water or water depth).</p>",
        "author_id": 423285776351,
        "vote_sum": 1,
        "vote_count": 1,
        "official": false,
        "html_url": "https://feedback.minecraft.net/hc/en-us/community/posts/4419696391053-Weeping-willow-trees-with-white-wood/comments/4420280832525",
        "created_at": "2022-01-12T08:23:19Z",
        "updated_at": "2022-01-19T22:34:34Z",
        "url": "https://minecraftfeedback.zendesk.com/api/v2/help_center/community/posts/4419696391053/comments/4420280832525.json",
        "post_id": 4419696391053,
        "non_author_editor_id": null,
        "non_author_updated_at": null
      },
      {
        "id": 4423231087373,
        "body": "<p>The bark could be used to make medicine that counteracts potions.</p>",
        "author_id": 1905050456007,
        "vote_sum": 2,
        "vote_count": 2,
        "official": false,
        "html_url": "https://feedback.minecraft.net/hc/en-us/community/posts/4419696391053-Weeping-willow-trees-with-white-wood/comments/4423231087373",
        "created_at": "2022-01-28T02:49:17Z",
        "updated_at": "2022-01-28T14:07:41Z",
        "url": "https://minecraftfeedback.zendesk.com/api/v2/help_center/community/posts/4419696391053/comments/4423231087373.json",
        "post_id": 4419696391053,
        "non_author_editor_id": null,
        "non_author_updated_at": null
      },
      {
        "id": 9076538327949,
        "body": "<p>I feel like a dark yellow would fit aesthetically&nbsp;</p>",
        "author_id": 8857719064973,
        "vote_sum": 0,
        "vote_count": 0,
        "official": false,
        "html_url": "https://feedback.minecraft.net/hc/en-us/community/posts/4419696391053-Weeping-willow-trees-with-white-wood/comments/9076538327949",
        "created_at": "2022-09-10T23:48:40Z",
        "updated_at": "2022-09-10T23:48:40Z",
        "url": "https://minecraftfeedback.zendesk.com/api/v2/help_center/community/posts/4419696391053/comments/9076538327949.json",
        "post_id": 4419696391053,
        "non_author_editor_id": null,
        "non_author_updated_at": null
      }
    ]
  },
  {
    "post_id": 4409476286093,
    "expected_comment_count": 4,
    "actual_comment_count": 4,
    "status": "ok",
    "comments": [
      {
        "id": 7230503007117,
        "body": "<p>this is good</p>",
        "author_id": 422846744291,
        "vote_sum": 4,
        "vote_count": 4,
        "official": false,
        "html_url": "https://feedback.minecraft.net/hc/en-us/community/posts/4409476286093-Combining-potion/comments/7230503007117",
        "created_at": "2022-06-27T14:36:24Z",
        "updated_at": "2023-12-03T02:04:23Z",
        "url": "https://minecraftfeedback.zendesk.com/api/v2/help_center/community/posts/4409476286093/comments/7230503007117.json",
        "post_id": 4409476286093,
        "non_author_editor_id": null,
        "non_author_updated_at": null
      },
      {
        "id": 18625247303565,
        "body": "<p><em>Rus</em>: <strong>Неплохо!</strong> тока надо сделать так чтобы двойное зелье дорого делалась.</p>\n<p><em>Eng:</em> <strong>Not bad!</strong> But gonna do more expensive for craft.</p>",
        "author_id": 18624972402061,
        "vote_sum": 3,
        "vote_count": 3,
        "official": false,
        "html_url": "https://feedback.minecraft.net/hc/en-us/community/posts/4409476286093-Combining-potion/comments/18625247303565",
        "created_at": "2023-08-17T15:47:56Z",
        "updated_at": "2023-12-03T02:04:23Z",
        "url": "https://minecraftfeedback.zendesk.com/api/v2/help_center/community/posts/4409476286093/comments/18625247303565.json",
        "post_id": 4409476286093,
        "non_author_editor_id": null,
        "non_author_updated_at": null
      },
      {
        "id": 21894385448333,
        "body": "<p>It’s Very Useful To Ether Kill Or Heal Players In Traps, Teams, And Even Against Or For Mobs!</p>",
        "author_id": 21894247046797,
        "vote_sum": 2,
        "vote_count": 2,
        "official": false,
        "html_url": "https://feedback.minecraft.net/hc/en-us/community/posts/4409476286093-Combining-potion/comments/21894385448333",
        "created_at": "2023-12-03T02:04:14Z",
        "updated_at": "2023-12-03T02:04:21Z",
        "url": "https://minecraftfeedback.zendesk.com/api/v2/help_center/community/posts/4409476286093/comments/21894385448333.json",
        "post_id": 4409476286093,
        "non_author_editor_id": null,
        "non_author_updated_at": null
      },
      {
        "id": 40459877668109,
        "body": "<p>Proszę zróbcie łączone mikstóry w kowadle pliska🥺🥺🥺</p>",
        "author_id": 40459893431053,
        "vote_sum": 0,
        "vote_count": 0,
        "official": false,
        "html_url": "https://feedback.minecraft.net/hc/en-us/community/posts/4409476286093-Combining-potion/comments/40459877668109",
        "created_at": "2025-10-20T07:39:04Z",
        "updated_at": "2025-10-20T16:36:51Z",
        "url": "https://minecraftfeedback.zendesk.com/api/v2/help_center/community/posts/4409476286093/comments/40459877668109.json",
        "post_id": 4409476286093,
        "non_author_editor_id": null,
        "non_author_updated_at": null
      }
    ]
  },
  {
    "post_id": 4408163639437,
    "expected_comment_count": 3,
    "actual_comment_count": 3,
    "status": "ok",
    "comments": [
      {
        "id": 4408427282957,
        "body": "<p>This is a really useful idea I’d do that in the game if I could </p>",
        "author_id": 419712644632,
        "vote_sum": 1,
        "vote_count": 1,
        "official": false,
        "html_url": "https://feedback.minecraft.net/hc/en-us/community/posts/4408163639437-Torch-in-offhand/comments/4408427282957",
        "created_at": "2021-09-02T16:35:03Z",
        "updated_at": "2024-01-04T23:44:36Z",
        "url": "https://minecraftfeedback.zendesk.com/api/v2/help_center/community/posts/4408163639437/comments/4408427282957.json",
        "post_id": 4408163639437,
        "non_author_editor_id": null,
        "non_author_updated_at": null
      },
      {
        "id": 19089229373837,
        "body": "<p>Idk why this doesn’t have more votes, this is a great idea.</p>",
        "author_id": 19089184574349,
        "vote_sum": 1,
        "vote_count": 1,
        "official": false,
        "html_url": "https://feedback.minecraft.net/hc/en-us/community/posts/4408163639437-Torch-in-offhand/comments/19089229373837",
        "created_at": "2023-08-31T23:15:31Z",
        "updated_at": "2024-01-04T23:44:35Z",
        "url": "https://minecraftfeedback.zendesk.com/api/v2/help_center/community/posts/4408163639437/comments/19089229373837.json",
        "post_id": 4408163639437,
        "non_author_editor_id": null,
        "non_author_updated_at": null
      },
      {
        "id": 23039683992205,
        "body": "<p>1) You can vote for your own post</p>\n<p>2) they didn't add the offhand to bedrock because of touchscreen devices. This is my solution to that:</p>\n<p><a href=\"https://feedback.minecraft.net/hc/en-us/community/posts/22935702808589-The-Offhand-Slot-On-Bedrock-Edition-Touchscreen-Devices\" target=\"_blank\" rel=\"nofollow noreferrer\">https://feedback.minecraft.net/hc/en-us/community/posts/22935702808589-The-Offhand-Slot-On-Bedrock-Edition-Touchscreen-Devices</a>&nbsp;</p>",
        "author_id": 400271757932,
        "vote_sum": 1,
        "vote_count": 1,
        "official": false,
        "html_url": "https://feedback.minecraft.net/hc/en-us/community/posts/4408163639437-Torch-in-offhand/comments/23039683992205",
        "created_at": "2024-01-09T04:08:13Z",
        "updated_at": "2024-01-09T16:23:02Z",
        "url": "https://minecraftfeedback.zendesk.com/api/v2/help_center/community/posts/4408163639437/comments/23039683992205.json",
        "post_id": 4408163639437,
        "non_author_editor_id": null,
        "non_author_updated_at": null
      }
    ]
  },
  {
    "post_id": 4404844097933,
    "expected_comment_count": 5,
    "actual_comment_count": 5,
    "status": "ok",
    "comments": [
      {
        "id": 4404937802509,
        "body": "<p>I like it! I've always thought that Mojang should add more crops, and I'm a fan of grapes.</p>",
        "author_id": 418397833152,
        "vote_sum": 2,
        "vote_count": 2,
        "official": false,
        "html_url": "https://feedback.minecraft.net/hc/en-us/community/posts/4404844097933-Grapes/comments/4404937802509",
        "created_at": "2021-07-13T15:36:03Z",
        "updated_at": "2023-08-06T07:43:42Z",
        "url": "https://minecraftfeedback.zendesk.com/api/v2/help_center/community/posts/4404844097933/comments/4404937802509.json",
        "post_id": 4404844097933,
        "non_author_editor_id": null,
        "non_author_updated_at": null
      },
      {
        "id": 4405166462349,
        "body": "<p>While I doubt Wine would be able to be added, being able to juice fruit would be cool! Maybe the player could get a special effect from drinking fruit juice or something.</p>",
        "author_id": 1900074664927,
        "vote_sum": 1,
        "vote_count": 1,
        "official": false,
        "html_url": "https://feedback.minecraft.net/hc/en-us/community/posts/4404844097933-Grapes/comments/4405166462349",
        "created_at": "2021-07-16T18:07:39Z",
        "updated_at": "2021-10-02T22:24:55Z",
        "url": "https://minecraftfeedback.zendesk.com/api/v2/help_center/community/posts/4404844097933/comments/4405166462349.json",
        "post_id": 4404844097933,
        "non_author_editor_id": null,
        "non_author_updated_at": null
      },
      {
        "id": 4405175285901,
        "body": "<p>Good idea. Maybe grapes in barrels slowly become wine.&nbsp;</p>",
        "author_id": 418466908192,
        "vote_sum": 2,
        "vote_count": 2,
        "official": false,
        "html_url": "https://feedback.minecraft.net/hc/en-us/community/posts/4404844097933-Grapes/comments/4405175285901",
        "created_at": "2021-07-16T22:12:45Z",
        "updated_at": "2022-01-16T04:38:19Z",
        "url": "https://minecraftfeedback.zendesk.com/api/v2/help_center/community/posts/4404844097933/comments/4405175285901.json",
        "post_id": 4404844097933,
        "non_author_editor_id": null,
        "non_author_updated_at": null
      },
      {
        "id": 4421157797389,
        "body": "<p>Could put in barrel to ferment</p>",
        "author_id": 423356862631,
        "vote_sum": 1,
        "vote_count": 1,
        "official": false,
        "html_url": "https://feedback.minecraft.net/hc/en-us/community/posts/4404844097933-Grapes/comments/4421157797389",
        "created_at": "2022-01-16T04:38:11Z",
        "updated_at": "2022-01-16T04:38:16Z",
        "url": "https://minecraftfeedback.zendesk.com/api/v2/help_center/community/posts/4404844097933/comments/4421157797389.json",
        "post_id": 4404844097933,
        "non_author_editor_id": null,
        "non_author_updated_at": null
      },
      {
        "id": 7680370691341,
        "body": "<p>This idea should really be Minecraft </p>",
        "author_id": 7680286801933,
        "vote_sum": 0,
        "vote_count": 0,
        "official": false,
        "html_url": "https://feedback.minecraft.net/hc/en-us/community/posts/4404844097933-Grapes/comments/7680370691341",
        "created_at": "2022-07-14T15:57:11Z",
        "updated_at": "2022-07-17T05:17:17Z",
        "url": "https://minecraftfeedback.zendesk.com/api/v2/help_center/community/posts/4404844097933/comments/7680370691341.json",
        "post_id": 4404844097933,
        "non_author_editor_id": null,
        "non_author_updated_at": null
      }
    ]
  },
  {
    "post_id": 360078322792,
    "expected_comment_count": 3,
    "actual_comment_count": 3,
    "status": "ok",
    "comments": [
      {
        "id": 360016090511,
        "body": "<p>I LOVE IT! Just recently I shared a suggestion for painted wood, and this would be the perfect thing of how to get painted wood!</p>",
        "author_id": 417213354972,
        "vote_sum": 3,
        "vote_count": 3,
        "official": false,
        "html_url": "https://feedback.minecraft.net/hc/en-us/community/posts/360078322792-Paint/comments/360016090511",
        "created_at": "2021-06-08T15:51:43Z",
        "updated_at": "2021-06-08T23:03:29Z",
        "url": "https://minecraftfeedback.zendesk.com/api/v2/help_center/community/posts/360078322792/comments/360016090511.json",
        "post_id": 360078322792,
        "non_author_editor_id": null,
        "non_author_updated_at": null
      },
      {
        "id": 26449668305549,
        "body": "<p>There should be an extra step to making paint. You would also need a honey bottle and slime block.</p>",
        "author_id": 21545826601869,
        "vote_sum": 2,
        "vote_count": 2,
        "official": false,
        "html_url": "https://feedback.minecraft.net/hc/en-us/community/posts/360078322792-Paint/comments/26449668305549",
        "created_at": "2024-05-04T07:32:06Z",
        "updated_at": "2024-05-04T07:32:07Z",
        "url": "https://minecraftfeedback.zendesk.com/api/v2/help_center/community/posts/360078322792/comments/26449668305549.json",
        "post_id": 360078322792,
        "non_author_editor_id": null,
        "non_author_updated_at": null
      },
      {
        "id": 38649074169101,
        "body": "<p>This is awesome, was thinking the same thing.</p>",
        "author_id": 38649011257741,
        "vote_sum": 0,
        "vote_count": 0,
        "official": false,
        "html_url": "https://feedback.minecraft.net/hc/en-us/community/posts/360078322792-Paint/comments/38649074169101",
        "created_at": "2025-08-07T17:11:35Z",
        "updated_at": "2025-08-07T17:11:35Z",
        "url": "https://minecraftfeedback.zendesk.com/api/v2/help_center/community/posts/360078322792/comments/38649074169101.json",
        "post_id": 360078322792,
        "non_author_editor_id": null,
        "non_author_updated_at": null
      }
    ]
  },
  {
    "post_id": 360078030291,
    "expected_comment_count": 3,
    "actual_comment_count": 3,
    "status": "ok",
    "comments": [
      {
        "id": 360015562812,
        "body": "<p>I'm surprised it doesn't already exist and I wish dogs could wear armor</p>",
        "author_id": 416710701132,
        "vote_sum": 0,
        "vote_count": 0,
        "official": false,
        "html_url": "https://feedback.minecraft.net/hc/en-us/community/posts/360078030291-Netherite-horse-armour/comments/360015562812",
        "created_at": "2021-05-25T22:40:10Z",
        "updated_at": "2021-05-25T23:26:30Z",
        "url": "https://minecraftfeedback.zendesk.com/api/v2/help_center/community/posts/360078030291/comments/360015562812.json",
        "post_id": 360078030291,
        "non_author_editor_id": null,
        "non_author_updated_at": null
      },
      {
        "id": 360015598471,
        "body": "<p>Why didn't they just add it in the first place?!?!?!?!</p>",
        "author_id": 417164047751,
        "vote_sum": 0,
        "vote_count": 0,
        "official": false,
        "html_url": "https://feedback.minecraft.net/hc/en-us/community/posts/360078030291-Netherite-horse-armour/comments/360015598471",
        "created_at": "2021-05-31T19:13:57Z",
        "updated_at": "2021-05-31T19:13:57Z",
        "url": "https://minecraftfeedback.zendesk.com/api/v2/help_center/community/posts/360078030291/comments/360015598471.json",
        "post_id": 360078030291,
        "non_author_editor_id": null,
        "non_author_updated_at": null
      },
      {
        "id": 16309230135949,
        "body": "<p>Just not in chests. There are no horses in the Nether.</p>",
        "author_id": 416461943171,
        "vote_sum": 1,
        "vote_count": 1,
        "official": false,
        "html_url": "https://feedback.minecraft.net/hc/en-us/community/posts/360078030291-Netherite-horse-armour/comments/16309230135949",
        "created_at": "2023-06-01T09:08:19Z",
        "updated_at": "2023-06-01T09:08:29Z",
        "url": "https://minecraftfeedback.zendesk.com/api/v2/help_center/community/posts/360078030291/comments/16309230135949.json",
        "post_id": 360078030291,
        "non_author_editor_id": null,
        "non_author_updated_at": null
      }
    ]
  },
  {
    "post_id": 360077632852,
    "expected_comment_count": 1,
    "actual_comment_count": 1,
    "status": "ok",
    "comments": [
      {
        "id": 360014821172,
        "body": "<p>I think an activator rail would be required for it to loop. The activator rail would only activate the jukebox if there is nothing being played by the jukebox. Otherwise I like it.</p>",
        "author_id": 406795646711,
        "vote_sum": 4,
        "vote_count": 4,
        "official": false,
        "html_url": "https://feedback.minecraft.net/hc/en-us/community/posts/360077632852-Jukebox-in-a-minecart/comments/360014821172",
        "created_at": "2021-04-05T20:42:18Z",
        "updated_at": "2024-02-29T19:11:43Z",
        "url": "https://minecraftfeedback.zendesk.com/api/v2/help_center/community/posts/360077632852/comments/360014821172.json",
        "post_id": 360077632852,
        "non_author_editor_id": null,
        "non_author_updated_at": null
      }
    ]
  },
  {
    "post_id": 360077382092,
    "expected_comment_count": 1,
    "actual_comment_count": 1,
    "status": "ok",
    "comments": [
      {
        "id": 360014756651,
        "body": "<p>I was thinking the same thing myself, this would be very helpful</p>",
        "author_id": 413320123612,
        "vote_sum": 2,
        "vote_count": 2,
        "official": false,
        "html_url": "https://feedback.minecraft.net/hc/en-us/community/posts/360077382092-Firework-table/comments/360014756651",
        "created_at": "2021-04-05T18:48:16Z",
        "updated_at": "2022-01-02T17:31:23Z",
        "url": "https://minecraftfeedback.zendesk.com/api/v2/help_center/community/posts/360077382092/comments/360014756651.json",
        "post_id": 360077382092,
        "non_author_editor_id": null,
        "non_author_updated_at": null
      }
    ]
  },
  {
    "post_id": 360077368832,
    "expected_comment_count": 3,
    "actual_comment_count": 3,
    "status": "ok",
    "comments": [
      {
        "id": 360014969692,
        "body": "<p>Agreed, there's quite some potential for iron and gold in this update</p>",
        "author_id": 374771791811,
        "vote_sum": 0,
        "vote_count": 0,
        "official": false,
        "html_url": "https://feedback.minecraft.net/hc/en-us/community/posts/360077368832-Iron-and-Gold-Stairs-and-Slabs-to-complement-Copper-Stairs-and-Slabs/comments/360014969692",
        "created_at": "2021-04-25T12:56:52Z",
        "updated_at": "2021-04-25T13:23:56Z",
        "url": "https://minecraftfeedback.zendesk.com/api/v2/help_center/community/posts/360077368832/comments/360014969692.json",
        "post_id": 360077368832,
        "non_author_editor_id": null,
        "non_author_updated_at": null
      },
      {
        "id": 4409652703501,
        "body": "<p>I have wanted this for years to make gold statues for my mount olympus map with out the need for a texture pack. *face plam \"why Mojang? WHY?\"<br><br>P.S. This should include walls and fence blocks similar to iron bars<br>Electrified copper fence anyone?</p>\n<p>.</p>",
        "author_id": 370419316232,
        "vote_sum": 0,
        "vote_count": 0,
        "official": false,
        "html_url": "https://feedback.minecraft.net/hc/en-us/community/posts/360077368832-Iron-and-Gold-Stairs-and-Slabs-to-complement-Copper-Stairs-and-Slabs/comments/4409652703501",
        "created_at": "2021-09-20T16:06:28Z",
        "updated_at": "2021-09-20T19:47:51Z",
        "url": "https://minecraftfeedback.zendesk.com/api/v2/help_center/community/posts/360077368832/comments/4409652703501.json",
        "post_id": 360077368832,
        "non_author_editor_id": null,
        "non_author_updated_at": null
      },
      {
        "id": 7751753274765,
        "body": "<p>Ever since I started playing Minecraft, I've been wishing for stairs, steps, fences, trapdoors, etc. made of iron, gold, lapis, emerald, redstone, and coal. Maybe these wishes will come true someday. There would be such great new decadent design possibilities.</p>",
        "author_id": 7751682107661,
        "vote_sum": 0,
        "vote_count": 0,
        "official": false,
        "html_url": "https://feedback.minecraft.net/hc/en-us/community/posts/360077368832-Iron-and-Gold-Stairs-and-Slabs-to-complement-Copper-Stairs-and-Slabs/comments/7751753274765",
        "created_at": "2022-07-18T10:13:45Z",
        "updated_at": "2022-07-27T20:36:10Z",
        "url": "https://minecraftfeedback.zendesk.com/api/v2/help_center/community/posts/360077368832/comments/7751753274765.json",
        "post_id": 360077368832,
        "non_author_editor_id": null,
        "non_author_updated_at": null
      }
    ]
  },
  {
    "post_id": 360077172151,
    "expected_comment_count": 8,
    "actual_comment_count": 8,
    "status": "ok",
    "comments": [
      {
        "id": 360014475292,
        "body": "<p>choccy milk</p>",
        "author_id": 405771019752,
        "vote_sum": 0,
        "vote_count": 0,
        "official": false,
        "html_url": "https://feedback.minecraft.net/hc/en-us/community/posts/360077172151-Chocolate-milk-Hot-Chocolate/comments/360014475292",
        "created_at": "2021-02-23T21:42:27Z",
        "updated_at": "2021-02-23T21:42:27Z",
        "url": "https://minecraftfeedback.zendesk.com/api/v2/help_center/community/posts/360077172151/comments/360014475292.json",
        "post_id": 360077172151,
        "non_author_editor_id": null,
        "non_author_updated_at": null
      },
      {
        "id": 360014412431,
        "body": "<p>haha i LOVE chocklet milk and hot coco PERFICKT</p>",
        "author_id": 411592424012,
        "vote_sum": 0,
        "vote_count": 0,
        "official": false,
        "html_url": "https://feedback.minecraft.net/hc/en-us/community/posts/360077172151-Chocolate-milk-Hot-Chocolate/comments/360014412431",
        "created_at": "2021-02-23T22:58:49Z",
        "updated_at": "2021-02-24T02:01:28Z",
        "url": "https://minecraftfeedback.zendesk.com/api/v2/help_center/community/posts/360077172151/comments/360014412431.json",
        "post_id": 360077172151,
        "non_author_editor_id": null,
        "non_author_updated_at": null
      },
      {
        "id": 360014413371,
        "body": "<p>What are the sweet berries for?&nbsp;</p>\n<p>&nbsp;</p>",
        "author_id": 411461528872,
        "vote_sum": 0,
        "vote_count": 0,
        "official": false,
        "html_url": "https://feedback.minecraft.net/hc/en-us/community/posts/360077172151-Chocolate-milk-Hot-Chocolate/comments/360014413371",
        "created_at": "2021-02-24T01:07:20Z",
        "updated_at": "2021-02-24T01:07:20Z",
        "url": "https://minecraftfeedback.zendesk.com/api/v2/help_center/community/posts/360077172151/comments/360014413371.json",
        "post_id": 360077172151,
        "non_author_editor_id": null,
        "non_author_updated_at": null
      },
      {
        "id": 360014413971,
        "body": "<p>Maybe sugar instead of sweet berries</p>\n<p>&nbsp;</p>",
        "author_id": 411461528872,
        "vote_sum": 2,
        "vote_count": 2,
        "official": false,
        "html_url": "https://feedback.minecraft.net/hc/en-us/community/posts/360077172151-Chocolate-milk-Hot-Chocolate/comments/360014413971",
        "created_at": "2021-02-24T02:41:48Z",
        "updated_at": "2022-01-02T05:05:38Z",
        "url": "https://minecraftfeedback.zendesk.com/api/v2/help_center/community/posts/360077172151/comments/360014413971.json",
        "post_id": 360077172151,
        "non_author_editor_id": null,
        "non_author_updated_at": null
      },
      {
        "id": 360014424611,
        "body": "<p>sugar is used for speed, not freeze resistance</p>",
        "author_id": 396761006771,
        "vote_sum": 1,
        "vote_count": 1,
        "official": false,
        "html_url": "https://feedback.minecraft.net/hc/en-us/community/posts/360077172151-Chocolate-milk-Hot-Chocolate/comments/360014424611",
        "created_at": "2021-02-24T19:06:50Z",
        "updated_at": "2021-02-24T23:56:10Z",
        "url": "https://minecraftfeedback.zendesk.com/api/v2/help_center/community/posts/360077172151/comments/360014424611.json",
        "post_id": 360077172151,
        "non_author_editor_id": null,
        "non_author_updated_at": null
      },
      {
        "id": 360014813891,
        "body": "<p>sweet berries should be a brewing/crafting item so i used them.</p>",
        "author_id": 396761006771,
        "vote_sum": 1,
        "vote_count": 1,
        "official": false,
        "html_url": "https://feedback.minecraft.net/hc/en-us/community/posts/360077172151-Chocolate-milk-Hot-Chocolate/comments/360014813891",
        "created_at": "2021-04-13T15:44:10Z",
        "updated_at": "2021-04-13T15:44:53Z",
        "url": "https://minecraftfeedback.zendesk.com/api/v2/help_center/community/posts/360077172151/comments/360014813891.json",
        "post_id": 360077172151,
        "non_author_editor_id": null,
        "non_author_updated_at": null
      },
      {
        "id": 360014813931,
        "body": "<p>and they have never been used in brewing</p>",
        "author_id": 396761006771,
        "vote_sum": 1,
        "vote_count": 1,
        "official": false,
        "html_url": "https://feedback.minecraft.net/hc/en-us/community/posts/360077172151-Chocolate-milk-Hot-Chocolate/comments/360014813931",
        "created_at": "2021-04-13T15:44:46Z",
        "updated_at": "2021-04-13T15:44:55Z",
        "url": "https://minecraftfeedback.zendesk.com/api/v2/help_center/community/posts/360077172151/comments/360014813931.json",
        "post_id": 360077172151,
        "non_author_editor_id": null,
        "non_author_updated_at": null
      },
      {
        "id": 13427755151501,
        "body": "<p>I think chocolate milk should restart potion effects instead of ending them like normal milk</p>\n<p>&nbsp;</p>",
        "author_id": 13400537481101,
        "vote_sum": 0,
        "vote_count": 0,
        "official": false,
        "html_url": "https://feedback.minecraft.net/hc/en-us/community/posts/360077172151-Chocolate-milk-Hot-Chocolate/comments/13427755151501",
        "created_at": "2023-02-25T20:11:22Z",
        "updated_at": "2023-04-19T20:41:23Z",
        "url": "https://minecraftfeedback.zendesk.com/api/v2/help_center/community/posts/360077172151/comments/13427755151501.json",
        "post_id": 360077172151,
        "non_author_editor_id": null,
        "non_author_updated_at": null
      }
    ]
  },
  {
    "post_id": 360077189892,
    "expected_comment_count": 3,
    "actual_comment_count": 3,
    "status": "ok",
    "comments": [
      {
        "id": 5112677890829,
        "body": "<p>More gun powder usage would make gunpowder more useful</p>\n<p>&nbsp;</p>",
        "author_id": 5112033680525,
        "vote_sum": 0,
        "vote_count": 0,
        "official": false,
        "html_url": "https://feedback.minecraft.net/hc/en-us/community/posts/360077189892-More-Gun-powder-usage/comments/5112677890829",
        "created_at": "2022-03-28T02:44:19Z",
        "updated_at": "2022-03-29T19:30:45Z",
        "url": "https://minecraftfeedback.zendesk.com/api/v2/help_center/community/posts/360077189892/comments/5112677890829.json",
        "post_id": 360077189892,
        "non_author_editor_id": null,
        "non_author_updated_at": null
      },
      {
        "id": 24431080603917,
        "body": "<p>I support cannon. and a musket that uses gun powder to shoot bullets which should be iron, copper or lead.<br>1 ingot required to make 3 bullets - more or less. The musket should be more powerful than the bow and crossbow (so that it feels worth using) but slower to reload so not too overpowered.</p>",
        "author_id": 24430683891981,
        "vote_sum": 1,
        "vote_count": 1,
        "official": false,
        "html_url": "https://feedback.minecraft.net/hc/en-us/community/posts/360077189892-More-Gun-powder-usage/comments/24431080603917",
        "created_at": "2024-02-25T07:25:15Z",
        "updated_at": "2024-02-26T16:38:50Z",
        "url": "https://minecraftfeedback.zendesk.com/api/v2/help_center/community/posts/360077189892/comments/24431080603917.json",
        "post_id": 360077189892,
        "non_author_editor_id": null,
        "non_author_updated_at": null
      },
      {
        "id": 41135273074061,
        "body": "<p>We definitely need this </p>",
        "author_id": 41135155204877,
        "vote_sum": 0,
        "vote_count": 0,
        "official": false,
        "html_url": "https://feedback.minecraft.net/hc/en-us/community/posts/360077189892-More-Gun-powder-usage/comments/41135273074061",
        "created_at": "2025-11-14T10:02:13Z",
        "updated_at": "2025-11-14T10:02:13Z",
        "url": "https://minecraftfeedback.zendesk.com/api/v2/help_center/community/posts/360077189892/comments/41135273074061.json",
        "post_id": 360077189892,
        "non_author_editor_id": null,
        "non_author_updated_at": null
      }
    ]
  },
  {
    "post_id": 360077050671,
    "expected_comment_count": 6,
    "actual_comment_count": 6,
    "status": "ok",
    "comments": [
      {
        "id": 4409172076557,
        "body": "<p>Totally agree with this post.</p>\n<p>It just doesn't make sense to not have infinity with mending.</p>",
        "author_id": 1901634349747,
        "vote_sum": 3,
        "vote_count": 3,
        "official": false,
        "html_url": "https://feedback.minecraft.net/hc/en-us/community/posts/360077050671-The-Fundamental-Flaw-of-the-Infinity-Bow/comments/4409172076557",
        "created_at": "2021-09-14T00:11:34Z",
        "updated_at": "2024-03-21T06:01:02Z",
        "url": "https://minecraftfeedback.zendesk.com/api/v2/help_center/community/posts/360077050671/comments/4409172076557.json",
        "post_id": 360077050671,
        "non_author_editor_id": null,
        "non_author_updated_at": null
      },
      {
        "id": 4417728059277,
        "body": "<p>Having just recently returned to this game and finding custom games no longer an option my whole view of playing has changed somewhat but I also understand a lot more about the why of certain mechanics.&nbsp; Anyway, after just recently fishing up an infinity bow with about 15% health on it, yes I agree with you about the repair costs and should allow mending.&nbsp;</p>\n<p>However, it is at the end of the day, a survival game which means nothing should last forever.&nbsp; As much as I want my awesome loot and crafted items to last forever that completely goes against the whole spirit of a survival game.&nbsp; If its was an MMORPG or FPS then yes loot should last forever but a game like this no.&nbsp; The idea being do I use my really good stuff and wear it down or use the not so good stuff, that I can replace a lot quicker and easier and save the top tier stuff?</p>\n<p>Just my thoughts on the matter.&nbsp; As much as I would love to have infinity and mending on a bow, kinda breaks the survival side.</p>",
        "author_id": 422912447631,
        "vote_sum": 3,
        "vote_count": 3,
        "official": false,
        "html_url": "https://feedback.minecraft.net/hc/en-us/community/posts/360077050671-The-Fundamental-Flaw-of-the-Infinity-Bow/comments/4417728059277",
        "created_at": "2021-12-25T22:21:06Z",
        "updated_at": "2024-03-21T06:01:03Z",
        "url": "https://minecraftfeedback.zendesk.com/api/v2/help_center/community/posts/360077050671/comments/4417728059277.json",
        "post_id": 360077050671,
        "non_author_editor_id": null,
        "non_author_updated_at": null
      },
      {
        "id": 6028818452493,
        "body": "<p>I have a fully enchanted bow with infinity, punch II, flame, power V, and unbreaking III. The repair first cost will be 9 levels. I used a web app to find the optimal enchantment order. I do think the infinity enchantment name is kind of gimmicky because it can only be used infinitely up until your bow becomes too expensive to repair. It would be more interesting and logical if you have to enchant the single arrow with infinity (would not work on stacks), then enchant your bow with mending.</p>",
        "author_id": 420784365451,
        "vote_sum": 3,
        "vote_count": 3,
        "official": false,
        "html_url": "https://feedback.minecraft.net/hc/en-us/community/posts/360077050671-The-Fundamental-Flaw-of-the-Infinity-Bow/comments/6028818452493",
        "created_at": "2022-05-05T19:00:31Z",
        "updated_at": "2024-03-21T06:01:24Z",
        "url": "https://minecraftfeedback.zendesk.com/api/v2/help_center/community/posts/360077050671/comments/6028818452493.json",
        "post_id": 360077050671,
        "non_author_editor_id": null,
        "non_author_updated_at": null
      },
      {
        "id": 6233992025101,
        "body": "<p>I agree, Mojang should fix this.</p>",
        "author_id": 417505595531,
        "vote_sum": 3,
        "vote_count": 3,
        "official": false,
        "html_url": "https://feedback.minecraft.net/hc/en-us/community/posts/360077050671-The-Fundamental-Flaw-of-the-Infinity-Bow/comments/6233992025101",
        "created_at": "2022-05-14T17:06:03Z",
        "updated_at": "2024-03-21T06:01:28Z",
        "url": "https://minecraftfeedback.zendesk.com/api/v2/help_center/community/posts/360077050671/comments/6233992025101.json",
        "post_id": 360077050671,
        "non_author_editor_id": null,
        "non_author_updated_at": null
      },
      {
        "id": 12434834775309,
        "body": "<p>It makes sense to me</p>\n<p>Either shoot infinitely until your bow breaks or</p>\n<p>shoot until you have no arrows left</p>",
        "author_id": 384823877951,
        "vote_sum": 2,
        "vote_count": 2,
        "official": false,
        "html_url": "https://feedback.minecraft.net/hc/en-us/community/posts/360077050671-The-Fundamental-Flaw-of-the-Infinity-Bow/comments/12434834775309",
        "created_at": "2023-01-21T12:16:40Z",
        "updated_at": "2024-03-21T06:01:30Z",
        "url": "https://minecraftfeedback.zendesk.com/api/v2/help_center/community/posts/360077050671/comments/12434834775309.json",
        "post_id": 360077050671,
        "non_author_editor_id": null,
        "non_author_updated_at": null
      },
      {
        "id": 23216075444493,
        "body": "<p>My bow said it would take 30 levels to fix last I checked but now that I have the levels I can’t repair it. So apparently I just lost my last repair for it. </p>",
        "author_id": 23216056581389,
        "vote_sum": 1,
        "vote_count": 1,
        "official": false,
        "html_url": "https://feedback.minecraft.net/hc/en-us/community/posts/360077050671-The-Fundamental-Flaw-of-the-Infinity-Bow/comments/23216075444493",
        "created_at": "2024-01-15T13:48:30Z",
        "updated_at": "2024-03-21T06:01:33Z",
        "url": "https://minecraftfeedback.zendesk.com/api/v2/help_center/community/posts/360077050671/comments/23216075444493.json",
        "post_id": 360077050671,
        "non_author_editor_id": null,
        "non_author_updated_at": null
      }
    ]
  },
  {
    "post_id": 360076926552,
    "expected_comment_count": 7,
    "actual_comment_count": 7,
    "status": "ok",
    "comments": [
      {
        "id": 360014150371,
        "body": "<p>محمد&nbsp;</p>",
        "author_id": 410321373131,
        "vote_sum": 1,
        "vote_count": 1,
        "official": false,
        "html_url": "https://feedback.minecraft.net/hc/en-us/community/posts/360076926552-Boat-with-item/comments/360014150371",
        "created_at": "2021-01-29T06:17:38Z",
        "updated_at": "2021-01-29T17:26:55Z",
        "url": "https://minecraftfeedback.zendesk.com/api/v2/help_center/community/posts/360076926552/comments/360014150371.json",
        "post_id": 360076926552,
        "non_author_editor_id": null,
        "non_author_updated_at": null
      },
      {
        "id": 360014221272,
        "body": "<p>محمد فضل</p>",
        "author_id": 410235186332,
        "vote_sum": 0,
        "vote_count": 0,
        "official": false,
        "html_url": "https://feedback.minecraft.net/hc/en-us/community/posts/360076926552-Boat-with-item/comments/360014221272",
        "created_at": "2021-01-29T17:27:38Z",
        "updated_at": "2021-01-29T17:27:38Z",
        "url": "https://minecraftfeedback.zendesk.com/api/v2/help_center/community/posts/360076926552/comments/360014221272.json",
        "post_id": 360076926552,
        "non_author_editor_id": null,
        "non_author_updated_at": null
      },
      {
        "id": 360014161831,
        "body": "<p>Ok</p>",
        "author_id": 410368504551,
        "vote_sum": 0,
        "vote_count": 0,
        "official": false,
        "html_url": "https://feedback.minecraft.net/hc/en-us/community/posts/360076926552-Boat-with-item/comments/360014161831",
        "created_at": "2021-01-30T07:10:00Z",
        "updated_at": "2021-01-30T07:10:00Z",
        "url": "https://minecraftfeedback.zendesk.com/api/v2/help_center/community/posts/360076926552/comments/360014161831.json",
        "post_id": 360076926552,
        "non_author_editor_id": null,
        "non_author_updated_at": null
      },
      {
        "id": 360014227152,
        "body": "<p>What</p>",
        "author_id": 410368504551,
        "vote_sum": 0,
        "vote_count": 0,
        "official": false,
        "html_url": "https://feedback.minecraft.net/hc/en-us/community/posts/360076926552-Boat-with-item/comments/360014227152",
        "created_at": "2021-01-30T07:10:16Z",
        "updated_at": "2021-01-30T07:10:16Z",
        "url": "https://minecraftfeedback.zendesk.com/api/v2/help_center/community/posts/360076926552/comments/360014227152.json",
        "post_id": 360076926552,
        "non_author_editor_id": null,
        "non_author_updated_at": null
      },
      {
        "id": 360014308811,
        "body": "<p>It’s putting stuff like chests, hoppers, TNT in a boat.</p>",
        "author_id": 410054439732,
        "vote_sum": 0,
        "vote_count": 0,
        "official": false,
        "html_url": "https://feedback.minecraft.net/hc/en-us/community/posts/360076926552-Boat-with-item/comments/360014308811",
        "created_at": "2021-02-13T23:51:59Z",
        "updated_at": "2021-02-13T23:51:59Z",
        "url": "https://minecraftfeedback.zendesk.com/api/v2/help_center/community/posts/360076926552/comments/360014308811.json",
        "post_id": 360076926552,
        "non_author_editor_id": null,
        "non_author_updated_at": null
      },
      {
        "id": 360014320531,
        "body": "<p>I agree! This should be a thing in both Bedrock and Java Editions of Minecraft!</p>",
        "author_id": 399593719512,
        "vote_sum": 0,
        "vote_count": 0,
        "official": false,
        "html_url": "https://feedback.minecraft.net/hc/en-us/community/posts/360076926552-Boat-with-item/comments/360014320531",
        "created_at": "2021-02-15T18:15:58Z",
        "updated_at": "2021-02-16T01:55:57Z",
        "url": "https://minecraftfeedback.zendesk.com/api/v2/help_center/community/posts/360076926552/comments/360014320531.json",
        "post_id": 360076926552,
        "non_author_editor_id": null,
        "non_author_updated_at": null
      },
      {
        "id": 14131123644941,
        "body": "<p>Hooray, My idea made it into Minecraft!</p>",
        "author_id": 14131062751757,
        "vote_sum": 0,
        "vote_count": 0,
        "official": false,
        "html_url": "https://feedback.minecraft.net/hc/en-us/community/posts/360076926552-Boat-with-item/comments/14131123644941",
        "created_at": "2023-03-19T18:56:22Z",
        "updated_at": "2023-03-19T18:56:23Z",
        "url": "https://minecraftfeedback.zendesk.com/api/v2/help_center/community/posts/360076926552/comments/14131123644941.json",
        "post_id": 360076926552,
        "non_author_editor_id": null,
        "non_author_updated_at": null
      }
    ]
  },
  {
    "post_id": 360076026471,
    "expected_comment_count": 3,
    "actual_comment_count": 3,
    "status": "ok",
    "comments": [
      {
        "id": 360013911471,
        "body": "<p>nice you got my vote</p>",
        "author_id": 405792396271,
        "vote_sum": 2,
        "vote_count": 2,
        "official": false,
        "html_url": "https://feedback.minecraft.net/hc/en-us/community/posts/360076026471-Fire-aspect-on-pickaxes-smelts-the-ore-it-mines/comments/360013911471",
        "created_at": "2021-01-04T01:48:29Z",
        "updated_at": "2023-02-10T23:08:53Z",
        "url": "https://minecraftfeedback.zendesk.com/api/v2/help_center/community/posts/360076026471/comments/360013911471.json",
        "post_id": 360076026471,
        "non_author_editor_id": null,
        "non_author_updated_at": null
      },
      {
        "id": 360013983752,
        "body": "<p>There are already various posts about pickaxes that smelt ores. This should have been a comment in one of those rather than a whole new post</p>",
        "author_id": 406280981491,
        "vote_sum": 2,
        "vote_count": 2,
        "official": false,
        "html_url": "https://feedback.minecraft.net/hc/en-us/community/posts/360076026471-Fire-aspect-on-pickaxes-smelts-the-ore-it-mines/comments/360013983752",
        "created_at": "2021-01-04T14:58:14Z",
        "updated_at": "2022-07-10T23:35:35Z",
        "url": "https://minecraftfeedback.zendesk.com/api/v2/help_center/community/posts/360076026471/comments/360013983752.json",
        "post_id": 360076026471,
        "non_author_editor_id": null,
        "non_author_updated_at": null
      },
      {
        "id": 360014053792,
        "body": "<p>I don't like this idea since furnaces will no longer be useful for smelting ores.</p>",
        "author_id": 406273121171,
        "vote_sum": 0,
        "vote_count": 0,
        "official": false,
        "html_url": "https://feedback.minecraft.net/hc/en-us/community/posts/360076026471-Fire-aspect-on-pickaxes-smelts-the-ore-it-mines/comments/360014053792",
        "created_at": "2021-01-12T03:43:52Z",
        "updated_at": "2021-01-12T03:43:52Z",
        "url": "https://minecraftfeedback.zendesk.com/api/v2/help_center/community/posts/360076026471/comments/360014053792.json",
        "post_id": 360076026471,
        "non_author_editor_id": null,
        "non_author_updated_at": null
      }
    ]
  },
  {
    "post_id": 360076141752,
    "expected_comment_count": 2,
    "actual_comment_count": 2,
    "status": "ok",
    "comments": [
      {
        "id": 360013914671,
        "body": "<p>Cool!</p>",
        "author_id": 408394839972,
        "vote_sum": 0,
        "vote_count": 0,
        "official": false,
        "html_url": "https://feedback.minecraft.net/hc/en-us/community/posts/360076141752-Rose-Gold/comments/360013914671",
        "created_at": "2021-01-04T13:50:53Z",
        "updated_at": "2021-01-05T00:00:21Z",
        "url": "https://minecraftfeedback.zendesk.com/api/v2/help_center/community/posts/360076141752/comments/360013914671.json",
        "post_id": 360076141752,
        "non_author_editor_id": null,
        "non_author_updated_at": null
      },
      {
        "id": 360013916611,
        "body": "<p>I feel like this is a pretty cool idea, except for the part where iron pickaxes can't break diamond. I don't think we should make new tools more useful by removing the functionality of old ones. I think all the rest is just fine, and people could have fun with pink armor. Other than that one thing, good idea! Thanks for actually fleshing it out. We need people to do that.</p>",
        "author_id": 394935776992,
        "vote_sum": 2,
        "vote_count": 2,
        "official": false,
        "html_url": "https://feedback.minecraft.net/hc/en-us/community/posts/360076141752-Rose-Gold/comments/360013916611",
        "created_at": "2021-01-04T16:22:33Z",
        "updated_at": "2021-01-15T16:14:32Z",
        "url": "https://minecraftfeedback.zendesk.com/api/v2/help_center/community/posts/360076141752/comments/360013916611.json",
        "post_id": 360076141752,
        "non_author_editor_id": null,
        "non_author_updated_at": null
      }
    ]
  },
  {
    "post_id": 360074675492,
    "expected_comment_count": 1,
    "actual_comment_count": 1,
    "status": "ok",
    "comments": [
      {
        "id": 360013437271,
        "body": "<p>Good idea ngl</p>",
        "author_id": 406425316771,
        "vote_sum": 1,
        "vote_count": 1,
        "official": false,
        "html_url": "https://feedback.minecraft.net/hc/en-us/community/posts/360074675492-Wall-and-Ceiling-Minecart-Rails/comments/360013437271",
        "created_at": "2020-11-14T20:40:09Z",
        "updated_at": "2021-07-25T10:35:20Z",
        "url": "https://minecraftfeedback.zendesk.com/api/v2/help_center/community/posts/360074675492/comments/360013437271.json",
        "post_id": 360074675492,
        "non_author_editor_id": null,
        "non_author_updated_at": null
      }
    ]
  },
  {
    "post_id": 360074523152,
    "expected_comment_count": 2,
    "actual_comment_count": 2,
    "status": "ok",
    "comments": [
      {
        "id": 360013433052,
        "body": "<p>This would add some nice creativity.</p>",
        "author_id": 385440894111,
        "vote_sum": 0,
        "vote_count": 0,
        "official": false,
        "html_url": "https://feedback.minecraft.net/hc/en-us/community/posts/360074523152-Milk-in-cauldron/comments/360013433052",
        "created_at": "2020-11-08T04:35:27Z",
        "updated_at": "2020-11-08T08:20:48Z",
        "url": "https://minecraftfeedback.zendesk.com/api/v2/help_center/community/posts/360074523152/comments/360013433052.json",
        "post_id": 360074523152,
        "non_author_editor_id": null,
        "non_author_updated_at": null
      },
      {
        "id": 360013479172,
        "body": "<p>we got snow in cauldrons. that's pretty close</p>",
        "author_id": 384243151452,
        "vote_sum": 0,
        "vote_count": 0,
        "official": false,
        "html_url": "https://feedback.minecraft.net/hc/en-us/community/posts/360074523152-Milk-in-cauldron/comments/360013479172",
        "created_at": "2020-11-12T06:24:33Z",
        "updated_at": "2020-11-12T06:24:33Z",
        "url": "https://minecraftfeedback.zendesk.com/api/v2/help_center/community/posts/360074523152/comments/360013479172.json",
        "post_id": 360074523152,
        "non_author_editor_id": null,
        "non_author_updated_at": null
      }
    ]
  },
  {
    "post_id": 360074040792,
    "expected_comment_count": 3,
    "actual_comment_count": 3,
    "status": "ok",
    "comments": [
      {
        "id": 360013162211,
        "body": "<p>I didn't think much about items or buildings, for example, but I tried to plan a start, so if you have more ideas, I'd love to see them in the comments&nbsp;</p>",
        "author_id": 398569734092,
        "vote_sum": 1,
        "vote_count": 1,
        "official": false,
        "html_url": "https://feedback.minecraft.net/hc/en-us/community/posts/360074040792-Minecraft-Update-idea-Housing/comments/360013162211",
        "created_at": "2020-10-21T01:59:31Z",
        "updated_at": "2020-10-22T22:06:24Z",
        "url": "https://minecraftfeedback.zendesk.com/api/v2/help_center/community/posts/360074040792/comments/360013162211.json",
        "post_id": 360074040792,
        "non_author_editor_id": null,
        "non_author_updated_at": null
      },
      {
        "id": 360015315891,
        "body": "<p>It's a mizzing wow</p>",
        "author_id": 415972199551,
        "vote_sum": 0,
        "vote_count": 0,
        "official": false,
        "html_url": "https://feedback.minecraft.net/hc/en-us/community/posts/360074040792-Minecraft-Update-idea-Housing/comments/360015315891",
        "created_at": "2021-05-03T03:05:13Z",
        "updated_at": "2021-05-03T03:05:13Z",
        "url": "https://minecraftfeedback.zendesk.com/api/v2/help_center/community/posts/360074040792/comments/360015315891.json",
        "post_id": 360074040792,
        "non_author_editor_id": null,
        "non_author_updated_at": null
      },
      {
        "id": 4404837688333,
        "body": "<p>Ola panas soy constructor de casas mansiones</p>",
        "author_id": 418365476352,
        "vote_sum": 0,
        "vote_count": 0,
        "official": false,
        "html_url": "https://feedback.minecraft.net/hc/en-us/community/posts/360074040792-Minecraft-Update-idea-Housing/comments/4404837688333",
        "created_at": "2021-07-12T07:12:26Z",
        "updated_at": "2021-07-12T07:12:26Z",
        "url": "https://minecraftfeedback.zendesk.com/api/v2/help_center/community/posts/360074040792/comments/4404837688333.json",
        "post_id": 360074040792,
        "non_author_editor_id": null,
        "non_author_updated_at": null
      }
    ]
  },
  {
    "post_id": 360073533011,
    "expected_comment_count": 1,
    "actual_comment_count": 1,
    "status": "ok",
    "comments": [
      {
        "id": 360013087452,
        "body": "<p>Really would be cool, but it would throw java pvp players out of the loop, if they are playing non 1.8 servers, or could be difficult for players using touch or controllers</p>",
        "author_id": 378916880591,
        "vote_sum": 0,
        "vote_count": 0,
        "official": false,
        "html_url": "https://feedback.minecraft.net/hc/en-us/community/posts/360073533011--Archeology-Artifacts-from-Minecraft-Dungeons/comments/360013087452",
        "created_at": "2020-10-07T00:41:02Z",
        "updated_at": "2020-10-07T02:55:39Z",
        "url": "https://minecraftfeedback.zendesk.com/api/v2/help_center/community/posts/360073533011/comments/360013087452.json",
        "post_id": 360073533011,
        "non_author_editor_id": null,
        "non_author_updated_at": null
      }
    ]
  },
  {
    "post_id": 360073482911,
    "expected_comment_count": 3,
    "actual_comment_count": 3,
    "status": "ok",
    "comments": [
      {
        "id": 360013051012,
        "body": "<p>Yeah they have a book on hermitcraft that is modded to allow them to make the item frame invisible</p>",
        "author_id": 404283794172,
        "vote_sum": 2,
        "vote_count": 2,
        "official": false,
        "html_url": "https://feedback.minecraft.net/hc/en-us/community/posts/360073482911-Shear-Item-frames/comments/360013051012",
        "created_at": "2020-10-04T15:55:01Z",
        "updated_at": "2020-10-05T01:41:53Z",
        "url": "https://minecraftfeedback.zendesk.com/api/v2/help_center/community/posts/360073482911/comments/360013051012.json",
        "post_id": 360073482911,
        "non_author_editor_id": null,
        "non_author_updated_at": null
      },
      {
        "id": 360013051352,
        "body": "<p>Thats where I got the idea from.</p>",
        "author_id": 398443962011,
        "vote_sum": 1,
        "vote_count": 1,
        "official": false,
        "html_url": "https://feedback.minecraft.net/hc/en-us/community/posts/360073482911-Shear-Item-frames/comments/360013051352",
        "created_at": "2020-10-04T16:27:37Z",
        "updated_at": "2020-10-05T01:41:55Z",
        "url": "https://minecraftfeedback.zendesk.com/api/v2/help_center/community/posts/360073482911/comments/360013051352.json",
        "post_id": 360073482911,
        "non_author_editor_id": null,
        "non_author_updated_at": null
      },
      {
        "id": 360012976311,
        "body": "<p>Thats pretty good way to implement it to survival</p>\n<p>or we can use slimeball on block and then glue item on it...</p>",
        "author_id": 393972008752,
        "vote_sum": 2,
        "vote_count": 2,
        "official": false,
        "html_url": "https://feedback.minecraft.net/hc/en-us/community/posts/360073482911-Shear-Item-frames/comments/360012976311",
        "created_at": "2020-10-04T16:51:29Z",
        "updated_at": "2020-10-05T18:17:06Z",
        "url": "https://minecraftfeedback.zendesk.com/api/v2/help_center/community/posts/360073482911/comments/360012976311.json",
        "post_id": 360073482911,
        "non_author_editor_id": null,
        "non_author_updated_at": null
      }
    ]
  },
  {
    "post_id": 360073412232,
    "expected_comment_count": 1,
    "actual_comment_count": 1,
    "status": "ok",
    "comments": [
      {
        "id": 360012893491,
        "body": "<p>I like this, but I think that you should be able to fish for them anywhere, and you could get them regardless of your luck of the sea level, however, they are extremely rare, and it is even rarer for them to be enchanted. They could also possibly come with curse of vanishing.&nbsp;</p>",
        "author_id": 393736925732,
        "vote_sum": 2,
        "vote_count": 2,
        "official": false,
        "html_url": "https://feedback.minecraft.net/hc/en-us/community/posts/360073412232-you-should-be-able-to-fish-for-tridents/comments/360012893491",
        "created_at": "2020-09-26T05:20:00Z",
        "updated_at": "2020-11-14T12:19:47Z",
        "url": "https://minecraftfeedback.zendesk.com/api/v2/help_center/community/posts/360073412232/comments/360012893491.json",
        "post_id": 360073412232,
        "non_author_editor_id": null,
        "non_author_updated_at": null
      }
    ]
  },
  {
    "post_id": 360073126971,
    "expected_comment_count": 9,
    "actual_comment_count": 9,
    "status": "ok",
    "comments": [
      {
        "id": 360012829372,
        "body": "<p>its a very good idea</p>",
        "author_id": 403292392131,
        "vote_sum": 1,
        "vote_count": 1,
        "official": false,
        "html_url": "https://feedback.minecraft.net/hc/en-us/community/posts/360073126971-Enchantment-extracting-table/comments/360012829372",
        "created_at": "2020-09-11T15:01:34Z",
        "updated_at": "2020-09-12T04:59:49Z",
        "url": "https://minecraftfeedback.zendesk.com/api/v2/help_center/community/posts/360073126971/comments/360012829372.json",
        "post_id": 360073126971,
        "non_author_editor_id": null,
        "non_author_updated_at": null
      },
      {
        "id": 360012756471,
        "body": "<p>Alternatively to fuel perhaps it would destroy the weapon after extraction </p>",
        "author_id": 389261478431,
        "vote_sum": 0,
        "vote_count": 0,
        "official": false,
        "html_url": "https://feedback.minecraft.net/hc/en-us/community/posts/360073126971-Enchantment-extracting-table/comments/360012756471",
        "created_at": "2020-09-12T05:44:21Z",
        "updated_at": "2020-09-12T05:44:21Z",
        "url": "https://minecraftfeedback.zendesk.com/api/v2/help_center/community/posts/360073126971/comments/360012756471.json",
        "post_id": 360073126971,
        "non_author_editor_id": null,
        "non_author_updated_at": null
      },
      {
        "id": 360012764651,
        "body": "<p>I have a similar idea but it takes off the enchantment off one thing and puts it on a new one. But it would use the lecture, a book &amp; quil, two emeralds, two Redstone and a nether star.</p>",
        "author_id": 403363733351,
        "vote_sum": 2,
        "vote_count": 2,
        "official": false,
        "html_url": "https://feedback.minecraft.net/hc/en-us/community/posts/360073126971-Enchantment-extracting-table/comments/360012764651",
        "created_at": "2020-09-13T17:49:28Z",
        "updated_at": "2022-06-05T19:09:27Z",
        "url": "https://minecraftfeedback.zendesk.com/api/v2/help_center/community/posts/360073126971/comments/360012764651.json",
        "post_id": 360073126971,
        "non_author_editor_id": null,
        "non_author_updated_at": null
      },
      {
        "id": 360012765371,
        "body": "<p>Maybe not the flower as it is nearly impossible to get... [keyword: nearly] perhaps something a little easier to obtain like wither skulls or better yet primed creeper heads... lol...</p>",
        "author_id": 390055216211,
        "vote_sum": 2,
        "vote_count": 2,
        "official": false,
        "html_url": "https://feedback.minecraft.net/hc/en-us/community/posts/360073126971-Enchantment-extracting-table/comments/360012765371",
        "created_at": "2020-09-13T19:53:24Z",
        "updated_at": "2022-06-05T19:09:39Z",
        "url": "https://minecraftfeedback.zendesk.com/api/v2/help_center/community/posts/360073126971/comments/360012765371.json",
        "post_id": 360073126971,
        "non_author_editor_id": null,
        "non_author_updated_at": null
      },
      {
        "id": 360012855791,
        "body": "<p> I think it must work like this: Sharpness V(sword) --&gt; Sharpness IV(Book). More bookshelfs = more chance to get Sharpness V or two enchantments on one book</p>",
        "author_id": 400520296692,
        "vote_sum": 2,
        "vote_count": 2,
        "official": false,
        "html_url": "https://feedback.minecraft.net/hc/en-us/community/posts/360073126971-Enchantment-extracting-table/comments/360012855791",
        "created_at": "2020-09-23T04:25:58Z",
        "updated_at": "2022-06-05T19:09:49Z",
        "url": "https://minecraftfeedback.zendesk.com/api/v2/help_center/community/posts/360073126971/comments/360012855791.json",
        "post_id": 360073126971,
        "non_author_editor_id": null,
        "non_author_updated_at": null
      },
      {
        "id": 360012972912,
        "body": "<p>There are already Grindstones that remove enchantments for EXP, but they should make it so you can put enchants on books.</p>",
        "author_id": 394369703871,
        "vote_sum": 3,
        "vote_count": 3,
        "official": false,
        "html_url": "https://feedback.minecraft.net/hc/en-us/community/posts/360073126971-Enchantment-extracting-table/comments/360012972912",
        "created_at": "2020-09-26T01:16:56Z",
        "updated_at": "2022-06-05T19:09:54Z",
        "url": "https://minecraftfeedback.zendesk.com/api/v2/help_center/community/posts/360073126971/comments/360012972912.json",
        "post_id": 360073126971,
        "non_author_editor_id": null,
        "non_author_updated_at": null
      },
      {
        "id": 360014672132,
        "body": "<p>i actually had the same idea if mojang add it it will be amazing!</p>",
        "author_id": 412725603852,
        "vote_sum": 0,
        "vote_count": 0,
        "official": false,
        "html_url": "https://feedback.minecraft.net/hc/en-us/community/posts/360073126971-Enchantment-extracting-table/comments/360014672132",
        "created_at": "2021-03-16T09:47:25Z",
        "updated_at": "2021-03-16T10:37:43Z",
        "url": "https://minecraftfeedback.zendesk.com/api/v2/help_center/community/posts/360073126971/comments/360014672132.json",
        "post_id": 360073126971,
        "non_author_editor_id": null,
        "non_author_updated_at": null
      },
      {
        "id": 6681073035277,
        "body": "<p>This is needed. It’s also expensive to make so you can’t really exploit it. Great thinking for the creator of this idea</p>",
        "author_id": 6681012779917,
        "vote_sum": 0,
        "vote_count": 0,
        "official": false,
        "html_url": "https://feedback.minecraft.net/hc/en-us/community/posts/360073126971-Enchantment-extracting-table/comments/6681073035277",
        "created_at": "2022-06-04T23:52:14Z",
        "updated_at": "2022-06-05T16:39:17Z",
        "url": "https://minecraftfeedback.zendesk.com/api/v2/help_center/community/posts/360073126971/comments/6681073035277.json",
        "post_id": 360073126971,
        "non_author_editor_id": null,
        "non_author_updated_at": null
      },
      {
        "id": 6689385304461,
        "body": "<p>Lets go!</p>",
        "author_id": 6333304334221,
        "vote_sum": 0,
        "vote_count": 0,
        "official": false,
        "html_url": "https://feedback.minecraft.net/hc/en-us/community/posts/360073126971-Enchantment-extracting-table/comments/6689385304461",
        "created_at": "2022-06-05T19:10:17Z",
        "updated_at": "2022-06-05T19:10:17Z",
        "url": "https://minecraftfeedback.zendesk.com/api/v2/help_center/community/posts/360073126971/comments/6689385304461.json",
        "post_id": 360073126971,
        "non_author_editor_id": null,
        "non_author_updated_at": null
      }
    ]
  },
  {
    "post_id": 360072821132,
    "expected_comment_count": 1,
    "actual_comment_count": 1,
    "status": "ok",
    "comments": [
      {
        "id": 360012681331,
        "body": "<p>Should also list what can be enchanted</p>",
        "author_id": 391306834532,
        "vote_sum": 3,
        "vote_count": 3,
        "official": false,
        "html_url": "https://feedback.minecraft.net/hc/en-us/community/posts/360072821132-Open-Enchanted-books/comments/360012681331",
        "created_at": "2020-09-03T19:40:37Z",
        "updated_at": "2022-09-23T20:34:37Z",
        "url": "https://minecraftfeedback.zendesk.com/api/v2/help_center/community/posts/360072821132/comments/360012681331.json",
        "post_id": 360072821132,
        "non_author_editor_id": null,
        "non_author_updated_at": null
      }
    ]
  }
]